<!-- This is a generated file. It is highly recommended that you DO NOT edit this file. --><iq:manifest xmlns:iq="http://www.garmin.com/xml/connectiq" version="2">
    <iq:application entry="BackToHomeDataFieldApp" id="96B3092103C94429B0F9E4927043FB0C" launcherIcon="@Drawables.LauncherIcon" minSdkVersion="1.2.0" name="@Strings.AppName" type="datafield">

        <iq:products>
            <iq:product id="fenix5"/>
            <iq:product id="fenix5x"/>
            <iq:product id="fenix5s"/>
            <iq:product id="fenix3"/>
            <iq:product id="fenix3_hr"/>
            <iq:product id="fenixchronos"/>
        </iq:products>

        <iq:permissions/>

        <iq:languages>
            <iq:language>fre</iq:language>
        </iq:languages>

    </iq:application>
</iq:manifest>
